php2py/__init__.py
php2py/ast_utils.py
php2py/cli.py
php2py/constants.py
php2py/etc/composer.json
php2py/etc/composer.lock
php2py/main.py
php2py/parser.py
php2py/php_ast.py
php2py/py_ast.py
php2py/translator/__init__.py
php2py/translator/base.py
php2py/translator/exprs.py
php2py/translator/scalars.py
php2py/translator/stmts.py
php2py/translator/translator.py
php2py/translator/utils.py
php2py-0.2.0.dist-info/LICENSE
php2py-0.2.0.dist-info/METADATA
php2py-0.2.0.dist-info/WHEEL
php2py-0.2.0.dist-info/entry_points.txt
php2py-0.2.0.dist-info/RECORD
