Metadata-Version: 2.1
Name: php2py
Version: 0.2.0
Summary: PHP to Python transpiler.
Home-page: https://github.com/sfermigier/php2py
Author: Abilian SAS
Author-email: sf@abilian.com
Requires-Python: >=3.9,<4
Classifier: Development Status :: 2 - Pre-Alpha
Classifier: Intended Audience :: Developers
Classifier: Natural Language :: English
Classifier: Programming Language :: Python :: 3
Classifier: Programming Language :: Python :: 3.9
Classifier: Programming Language :: Python :: 3.10
Classifier: Programming Language :: Python :: 3.11
Requires-Dist: astor (>=0.8.1,<0.9.0)
Requires-Dist: astpretty (>=3.0.0,<4.0.0)
Requires-Dist: attrs (>=23.1.0,<24.0.0)
Requires-Dist: cleez (>=0.1.11,<0.2.0)
Requires-Dist: click (>=8.1.3,<9.0.0)
Requires-Dist: devtools (>=0.11.0,<0.12.0)
Requires-Dist: icecream (>=2.1.3,<3.0.0)
Requires-Dist: platformdirs (>=3.5.1,<4.0.0)
Requires-Dist: rich (>=13.4.1,<14.0.0)
